setup.py
imagesim/__init__.py
imagesim/imagesim.py
imagesim.egg-info/PKG-INFO
imagesim.egg-info/SOURCES.txt
imagesim.egg-info/dependency_links.txt
imagesim.egg-info/requires.txt
imagesim.egg-info/top_level.txt